kivy_garden/mapview/__init__.py
kivy_garden/mapview/_version.py
kivy_garden/mapview/clustered_marker_layer.py
kivy_garden/mapview/constants.py
kivy_garden/mapview/downloader.py
kivy_garden/mapview/geojson.py
kivy_garden/mapview/mbtsource.py
kivy_garden/mapview/source.py
kivy_garden/mapview/types.py
kivy_garden/mapview/utils.py
kivy_garden/mapview/view.py
kivy_garden/mapview/icons/cluster.png
kivy_garden/mapview/icons/marker.png
mapview-1.0.6.data/data/icons/cluster.png
mapview-1.0.6.data/data/icons/marker.png
mapview-1.0.6.dist-info/AUTHORS.txt
mapview-1.0.6.dist-info/LICENSE.txt
mapview-1.0.6.dist-info/METADATA
mapview-1.0.6.dist-info/WHEEL
mapview-1.0.6.dist-info/top_level.txt
mapview-1.0.6.dist-info/RECORD
