Metadata-Version: 2.1
Name: mapview
Version: 1.0.6
Summary: A kivy garden mapview demo.
Home-page: https://github.com/kivy-garden/mapview
Author: Kivy
Author-email: kivy@kivy.org
License: UNKNOWN
Project-URL: Bug Reports, https://github.com/kivy-garden/mapview/issues
Project-URL: Source, https://github.com/kivy-garden/mapview
Keywords: Kivy kivy-garden
Platform: UNKNOWN
Classifier: Development Status :: 4 - Beta
Classifier: Intended Audience :: Developers
Classifier: Topic :: Software Development :: Libraries
Classifier: License :: OSI Approved :: MIT License
Classifier: Programming Language :: Python :: 3.5
Classifier: Programming Language :: Python :: 3.6
Classifier: Programming Language :: Python :: 3.7
Classifier: Programming Language :: Python :: 3.8
Provides-Extra: dev
Provides-Extra: ci
License-File: LICENSE.txt
License-File: AUTHORS.txt
